uidis/__init__.py
uidis/app.py
uidis/buttons.py
uidis/enums.py
uidis/example_nav.py
uidis/icons.py
uidis/inputs.py
uidis/layout.py
uidis/lookups.py
uidis/nav.py
uidis/scopes.py
uidis/shared.py
uidis/shorts.py
uidis/text.py
uidis/transfers.py
uidis/assets/index.css
uidis/assets/index.html
uidis/assets/index.js
uidis/assets/lookups/icon
uidis-0.1.1.dist-info/METADATA
uidis-0.1.1.dist-info/WHEEL
uidis-0.1.1.dist-info/RECORD
