Metadata-Version: 2.4
Name: uidis
Version: 0.1.1
Summary: Python Web UI App Framework
Requires-Python: >=3.10
Requires-Dist: fastapi[standard]>=0.115.8
Requires-Dist: msgspec>=0.19.0
Requires-Dist: requests>=2.32.3
